{"apis":[{"operations":[{"parameters":[{"dataType":"string","description":"Your access API key","paramType":"path","name":"api_key","threescale_name":"app_ids"},{"dataType":"string","description":"Your access API secret","paramType":"query","name":"api_secret","threescale_name":"app_keys"}],"group":"mediafile","description":"<p>List the media files stored at APIdaze.</p>","summary":"Media File List","httpMethod":"GET"}],"path":"/{api_key}/mediafiles"},{"operations":[{"parameters":[{"dataType":"string","description":"Your access API key","paramType":"path","name":"api_key","threescale_name":"app_ids"},{"dataType":"string","description":"Your access API secret","paramType":"query","name":"api_secret","threescale_name":"app_keys"}],"group":"mediafile","description":"<p>Upload a media file so we can play it locally in a <playback/> XML script tag. This action cannot be performed from the developer portal, but the following curl example might help :</p><p>curl 'https://api2.apidaze.io/5dg4hw9y/mediafiles' -F 'api_secret=re41tr525ed72233en0769dreop05283' -F 'name=myfile.wav' -F 'mediafile=@/tmp/myfile.wav'</p>","summary":"Media File Upload","httpMethod":"POST"}],"path":"/{api_key}/mediafiles"},{"operations":[{"parameters":[{"dataType":"string","description":"Your access API key","paramType":"path","name":"api_key","threescale_name":"app_ids"},{"dataType":"string","description":"Your access API secret","paramType":"query","name":"api_secret","threescale_name":"app_keys"},{"required":true,"dataType":"string","description":"Name of the file to delete","paramType":"path","name":"name"}],"group":"mediafile","description":"<p>Delete a media file stored at APIdaze.</p>","summary":"Media File Delete","httpMethod":"DELETE"}],"path":"/{api_key}/mediafiles"},{"operations":[{"parameters":[{"dataType":"string","description":"Your access API key","paramType":"path","name":"api_key","threescale_name":"app_ids"},{"dataType":"string","description":"Your access API secret","paramType":"query","name":"api_secret","threescale_name":"app_keys"}],"group":"validate","description":"<p>Validates your API key and secret.</p>","summary":"Validate API key/secret","httpMethod":"GET"}],"path":"/{api_key}/validates"}],"basePath":"https://api2.apidaze.io","apiVersion":"1.1"}
